{
  "project_info": {
    "project_number": "882925310788",
    "project_id": "reto2---chat",
    "storage_bucket": "reto2---chat.appspot.com"
  },
  "client": [
    {
      "client_info": {
        "mobilesdk_app_id": "1:882925310788:android:2349ce58da418019c7bd11",
        "android_client_info": {
          "package_name": "com.example.reto2chat"
        }
      },
      "oauth_client": [],
      "api_key": [
        {
          "current_key": "AIzaSyAnsMftxr9-sPsactWqVRDpSuWC9bPGed0"
        }
      ],
      "services": {
        "appinvite_service": {
          "other_platform_oauth_client": []
        }
      }
    }
  ],
  "configuration_version": "1"
}